two_to_tango/__init__.py
two_to_tango/_nbdev.py
two_to_tango/approach.py
two_to_tango/cli.py
two_to_tango/combo.py
two_to_tango/eval.py
two_to_tango/features.py
two_to_tango/model.py
two_to_tango/prep.py
two_to_tango/utils.py
two_to_tango-0.0.4.dist-info/LICENSE
two_to_tango-0.0.4.dist-info/METADATA
two_to_tango-0.0.4.dist-info/WHEEL
two_to_tango-0.0.4.dist-info/entry_points.txt
two_to_tango-0.0.4.dist-info/top_level.txt
two_to_tango-0.0.4.dist-info/RECORD
