Metadata-Version: 2.1
Name: two-to-tango
Version: 0.0.4
Summary: Tango automatically detects duplicate bugs that are captured in bug reports that contain videos detailing the bug
Home-page: https://github.com/ncoop57/two_to_tango
Author: Nathan Cooper
Author-email: nacooper01@email.wm.edu
License: Apache Software License 2.0
Keywords: deep learning duplicate video detection android bug report
Platform: UNKNOWN
Classifier: Development Status :: 3 - Alpha
Classifier: Intended Audience :: Science/Research
Classifier: License :: OSI Approved :: Apache Software License
Classifier: Natural Language :: English
Classifier: Programming Language :: Python :: 3.6
Classifier: Programming Language :: Python :: 3.7
Classifier: Programming Language :: Python :: 3.8
Requires-Python: >=3.6
Requires-Dist: fastcore (==1.3.10)
Requires-Dist: fastprogress (==0.2.1)
Requires-Dist: ffmpeg-python (==0.2.0)
Requires-Dist: matplotlib (==3.1.1)
Requires-Dist: more-itertools (==8.0.2)
Requires-Dist: numpy (==1.19.1)
Requires-Dist: opencv-contrib-python (==3.4.1.15)
Requires-Dist: opencv-python (==3.4.1.15)
Requires-Dist: pandas (==0.25.3)
Requires-Dist: pytesseract (==0.3.5)
Requires-Dist: pytorch-lightning (==0.9.0)
Requires-Dist: requests (==2.25.0)
Requires-Dist: scikit-learn (==0.22.1)
Requires-Dist: torch (==1.6.0)
Requires-Dist: torchvision (==0.7.0)
Requires-Dist: tqdm (==4.41.1)
